{
	"format_version": "1.8.0",
	"animations": {
		"animation.glow_worm.walk": {
			"loop": true,
			"animation_length": 0.5,
			"bones": {
				"bodyPart_2": {
					"scale": {
						"0.0": [1, 1, 1],
						"0.1167": [1, 1, 1.75],
						"0.4333": [1, 1, 1]
					}
				},
				"bodyPart_0": {
					"rotation": {
						"0.0": [0, 0, 0],
						"0.0833": [-35, 0, 0],
						"0.1667": [0, 0, 0]
					},
					"position": {
						"0.0": [0, 0, 0],
						"0.0833": [0, 0, 0.25],
						"0.2833": [0, 0, 0]
					}
				}
			}
		}
	}
}